Metadata-Version: 2.1
Name: pybboxes
Version: 0.2.0
Summary: Light Weight Toolkit for Bounding Boxes
Home-page: https://github.com/devrimcavusoglu/pybboxes
Author: Devrim Cavusoglu
License: MIT
Keywords: machine-learning,deep-learning,image-processing,pytorch,tensorflow,numpy,bounding-box,iou,computer-vision,cv
Classifier: Development Status :: 5 - Production/Stable
Classifier: Operating System :: OS Independent
Classifier: Intended Audience :: Developers
Classifier: Intended Audience :: Science/Research
Classifier: Programming Language :: Python :: 3
Classifier: Programming Language :: Python :: 3.8
Classifier: Programming Language :: Python :: 3.9
Classifier: Programming Language :: Python :: 3.10
Classifier: Programming Language :: Python :: 3.11
Classifier: Topic :: Software Development :: Libraries
Classifier: Topic :: Software Development :: Libraries :: Python Modules
Classifier: Topic :: Education
Classifier: Topic :: Scientific/Engineering
Classifier: Topic :: Scientific/Engineering :: Artificial Intelligence
Requires-Python: >=3.8
License-File: LICENSE
Requires-Dist: numpy==1.24.2
Requires-Dist: pycocotools==2.0.6
Requires-Dist: pyyaml==6.0
Provides-Extra: dev
Requires-Dist: black==22.3.0; extra == "dev"
Requires-Dist: click==8.0.4; extra == "dev"
Requires-Dist: deepdiff==5.5.0; extra == "dev"
Requires-Dist: flake8==3.9.2; extra == "dev"
Requires-Dist: isort==5.9.2; extra == "dev"
Requires-Dist: pytest>=7.0.1; extra == "dev"
Requires-Dist: pytest-cov>=3.0.0; extra == "dev"
Requires-Dist: pytest-timeout>=2.1.0; extra == "dev"
Requires-Dist: pytest-depends>=1.0.1; extra == "dev"
Requires-Dist: huggingface-hub>=0.25.0; extra == "dev"
Requires-Dist: importlib-metadata<4.3,>=1.1.0; python_version < "3.8" and extra == "dev"
